{"BaseModel.5132ba0e-d2f0-4ec4-ae82-4443595edac9": {"__class__": "BaseModel", "id": "5132ba0e-d2f0-4ec4-ae82-4443595edac9", "created_at": "2022-08-07T08:07:29.040323", "updated_at": "2022-08-07T08:07:29.046594", "name": "My First Model", "my_number": 89}, "BaseModel.41684fff-be9f-491a-b7b6-4106ac8b2069": {"__class__": "BaseModel", "id": "41684fff-be9f-491a-b7b6-4106ac8b2069", "created_at": "2022-08-07T08:09:14.343842", "updated_at": "2022-08-07T08:09:14.343913", "name": "My First Model", "my_number": 89}, "BaseModel.8209d12b-fb01-422b-a27b-197e4efc9466": {"__class__": "BaseModel", "id": "8209d12b-fb01-422b-a27b-197e4efc9466", "created_at": "2022-08-07T08:37:05.236815", "updated_at": "2022-08-07T08:37:05.236826", "name": "My_First_Model", "my_number": 89}, "BaseModel.a3082b99-6a4c-4bcf-b389-e213ba9c9bb1": {"__class__": "BaseModel", "id": "a3082b99-6a4c-4bcf-b389-e213ba9c9bb1", "created_at": "2022-08-07T08:37:11.142751", "updated_at": "2022-08-07T08:37:11.142765", "name": "My_First_Model", "my_number": 89}, "BaseModel.d897849d-0db5-4406-a0e8-fbf2288ce837": {"__class__": "BaseModel", "id": "d897849d-0db5-4406-a0e8-fbf2288ce837", "created_at": "2022-08-07T08:37:30.336527", "updated_at": "2022-08-07T08:37:30.336541", "name": "My_First_Model", "my_number": 89}, "BaseModel.7c5a48f8-d0ca-4888-a361-38eb40419913": {"__class__": "BaseModel", "id": "7c5a48f8-d0ca-4888-a361-38eb40419913", "created_at": "2022-08-07T10:22:58.936975", "updated_at": "2022-08-07T10:22:58.937248", "name": "My First Model", "my_number": 89}, "BaseModel.47175c78-6f12-4495-a8a8-90bfede0165c": {"__class__": "BaseModel", "id": "47175c78-6f12-4495-a8a8-90bfede0165c", "created_at": "2022-08-07T10:24:05.938223", "updated_at": "2022-08-07T10:24:05.946520", "name": "My First Model", "my_number": 89}}